deepts/__init__.py
deepts-0.0.1.dist-info/LICENSE
deepts-0.0.1.dist-info/METADATA
deepts-0.0.1.dist-info/WHEEL
deepts-0.0.1.dist-info/top_level.txt
deepts-0.0.1.dist-info/RECORD
